sql_schema_builder/MySQLSchema.py
sql_schema_builder/PgSQLSchema.py
sql_schema_builder/SQLSchemaBuilder.py
sql_schema_builder/__init__.py
sql_schema_builder-1.6.2.dist-info/licenses/LICENSE
sql_schema_builder-1.6.2.dist-info/METADATA
sql_schema_builder-1.6.2.dist-info/WHEEL
sql_schema_builder-1.6.2.dist-info/top_level.txt
sql_schema_builder-1.6.2.dist-info/RECORD
