Metadata-Version: 2.4
Name: sql-schema-builder
Version: 1.6.2
Summary: Library to keep SQL database schema up to date with your code.
Home-page: https://github.com/mmeinardi-ganymede/sql-schema-builder
Download-URL: https://github.com/mmeinardi-ganymede/sql-schema-builder/tarball/1.6.2
Author: Ganymede
Author-email: mmeinardi@ganymede.eu
License: MIT License
Keywords: pymysql psycopg sql schema builder mysql ddl migration migrate
License-File: LICENSE
Requires-Dist: pymysql
Requires-Dist: psycopg[binary,pool]
Dynamic: author
Dynamic: author-email
Dynamic: download-url
Dynamic: home-page
Dynamic: keywords
Dynamic: license
Dynamic: license-file
Dynamic: requires-dist
Dynamic: summary
